{
  "extends": [
    "tslint:recommended",
    "tslint-eslint-rules"
  ],
  "rules": {
    "class-name": true,
    "comment-format": [
      true,
      "check-space"
    ],
    "max-classes-per-file": 2,
    "member-ordering": false,
    "no-console": false,
    "no-duplicate-variable": true,
    "no-eval": true,
    "no-internal-module": true,
    "no-namespace": false,
    "no-string-literal": false,
    "no-trailing-whitespace": true,
    "no-var-keyword": true,
    "object-literal-shorthand": false,
    "object-literal-sort-keys": false,
    "one-line": [
      true,
      "check-catch",
      "check-else",
      "check-open-brace",
      "check-whitespace"
    ],
    "quotemark": [
      true,
      "single"
    ],
    "semicolon": [
      true,
      "always"
    ],
    "ter-indent": [true, 2],
    "triple-equals": [
      true,
      "allow-null-check"
    ],
    "typedef-whitespace": [
      true,
      {
        "call-signature": "nospace",
        "index-signature": "nospace",
        "parameter": "nospace",
        "property-declaration": "nospace",
        "variable-declaration": "nospace"
      }
    ],
    "variable-name": [
      true,
      "ban-keywords"
    ],
    "whitespace": [
      true,
      "check-branch",
      "check-decl",
      "check-operator",
      "check-separator",
      "check-type"
    ]
  }
}
